{
"meta":{"test_sets":[],"test_metrics":[],"learn_metrics":[{"best_value":"Min","name":"Logloss"}],"launch_mode":"Train","parameters":"","iteration_count":100,"learn_sets":["learn"],"name":"experiment"},
"iterations":[
{"learn":[0.6363997037],"iteration":0,"passed_time":0.01187875728,"remaining_time":1.175996971},
{"learn":[0.5897909161],"iteration":1,"passed_time":0.02021221372,"remaining_time":0.9903984723},
{"learn":[0.5507337575],"iteration":2,"passed_time":0.03144759202,"remaining_time":1.016805475},
{"learn":[0.5184128385],"iteration":3,"passed_time":0.04033711705,"remaining_time":0.9680908092},
{"learn":[0.4905447809],"iteration":4,"passed_time":0.04784159518,"remaining_time":0.9089903083},
{"learn":[0.4670354807],"iteration":5,"passed_time":0.0564081546,"remaining_time":0.8837277553},
{"learn":[0.4467529603],"iteration":6,"passed_time":0.0645283773,"remaining_time":0.8573055841},
{"learn":[0.4293118414],"iteration":7,"passed_time":0.0738600422,"remaining_time":0.8493904853},
{"learn":[0.4139742122],"iteration":8,"passed_time":0.08096634188,"remaining_time":0.818659679},
{"learn":[0.4007051087],"iteration":9,"passed_time":0.08944455425,"remaining_time":0.8050009882},
{"learn":[0.3892378133],"iteration":10,"passed_time":0.09661724737,"remaining_time":0.7817213651},
{"learn":[0.3793495671],"iteration":11,"passed_time":0.1053125078,"remaining_time":0.7722917237},
{"learn":[0.3708646475],"iteration":12,"passed_time":0.1131979136,"remaining_time":0.7575552681},
{"learn":[0.3634687408],"iteration":13,"passed_time":0.1216747364,"remaining_time":0.7474305237},
{"learn":[0.3569270987],"iteration":14,"passed_time":0.1309333843,"remaining_time":0.7419558444},
{"learn":[0.3510022974],"iteration":15,"passed_time":0.1400621198,"remaining_time":0.735326129},
{"learn":[0.3458261645],"iteration":16,"passed_time":0.1481835971,"remaining_time":0.7234846209},
{"learn":[0.3412532832],"iteration":17,"passed_time":0.1561691398,"remaining_time":0.7114371923},
{"learn":[0.3373827588],"iteration":18,"passed_time":0.1646807341,"remaining_time":0.7020599717},
{"learn":[0.3340251716],"iteration":19,"passed_time":0.1748736207,"remaining_time":0.6994944829},
{"learn":[0.3309898408],"iteration":20,"passed_time":0.1838014399,"remaining_time":0.6914435121},
{"learn":[0.3282457179],"iteration":21,"passed_time":0.1920180058,"remaining_time":0.6807911114},
{"learn":[0.3260577368],"iteration":22,"passed_time":0.200392642,"remaining_time":0.6708797144},
{"learn":[0.3240413823],"iteration":23,"passed_time":0.2092925492,"remaining_time":0.662759739},
{"learn":[0.3221920169],"iteration":24,"passed_time":0.2170172722,"remaining_time":0.6510518165},
{"learn":[0.3205065349],"iteration":25,"passed_time":0.2270703989,"remaining_time":0.6462772892},
{"learn":[0.3190092606],"iteration":26,"passed_time":0.2354443348,"remaining_time":0.63657172},
{"learn":[0.3176968576],"iteration":27,"passed_time":0.2439954774,"remaining_time":0.6274169418},
{"learn":[0.3165938736],"iteration":28,"passed_time":0.2513691144,"remaining_time":0.6154209352},
{"learn":[0.3155454133],"iteration":29,"passed_time":0.259336936,"remaining_time":0.6051195173},
{"learn":[0.3147297184],"iteration":30,"passed_time":0.2672602916,"remaining_time":0.5948696814},
{"learn":[0.3139732714],"iteration":31,"passed_time":0.2753817192,"remaining_time":0.5851861532},
{"learn":[0.3133956684],"iteration":32,"passed_time":0.2835471714,"remaining_time":0.5756866813},
{"learn":[0.3127954574],"iteration":33,"passed_time":0.2915203731,"remaining_time":0.5658924889},
{"learn":[0.3122291989],"iteration":34,"passed_time":0.2994378381,"remaining_time":0.5560988421},
{"learn":[0.3117756761],"iteration":35,"passed_time":0.3084448506,"remaining_time":0.5483464011},
{"learn":[0.3113490327],"iteration":36,"passed_time":0.3164777222,"remaining_time":0.538867473},
{"learn":[0.3109792359],"iteration":37,"passed_time":0.3267299987,"remaining_time":0.5330857874},
{"learn":[0.3107167611],"iteration":38,"passed_time":0.3359041013,"remaining_time":0.5253884661},
{"learn":[0.3104381266],"iteration":39,"passed_time":0.3441844762,"remaining_time":0.5162767143},
{"learn":[0.3101778912],"iteration":40,"passed_time":0.3524050371,"remaining_time":0.5071194436},
{"learn":[0.309951928],"iteration":41,"passed_time":0.3596072572,"remaining_time":0.496600498},
{"learn":[0.3097439926],"iteration":42,"passed_time":0.3669979452,"remaining_time":0.4864856482},
{"learn":[0.3095637364],"iteration":43,"passed_time":0.3750412201,"remaining_time":0.4773251892},
{"learn":[0.3094323928],"iteration":44,"passed_time":0.3832394599,"remaining_time":0.4684037843},
{"learn":[0.3092982752],"iteration":45,"passed_time":0.3910468752,"remaining_time":0.4590550274},
{"learn":[0.3091831676],"iteration":46,"passed_time":0.3985493332,"remaining_time":0.4494279715},
{"learn":[0.3090925924],"iteration":47,"passed_time":0.4068199194,"remaining_time":0.4407215793},
{"learn":[0.30906756],"iteration":48,"passed_time":0.4142940477,"remaining_time":0.4312040088},
{"learn":[0.3089600201],"iteration":49,"passed_time":0.4221859336,"remaining_time":0.4221859336},
{"learn":[0.3088693326],"iteration":50,"passed_time":0.4295002681,"remaining_time":0.4126571203},
{"learn":[0.3088123838],"iteration":51,"passed_time":0.4387845453,"remaining_time":0.405031888},
{"learn":[0.3087308851],"iteration":52,"passed_time":0.4467727091,"remaining_time":0.3961946665},
{"learn":[0.3086711806],"iteration":53,"passed_time":0.4549788957,"remaining_time":0.3875746149},
{"learn":[0.3086572511],"iteration":54,"passed_time":0.4626413639,"remaining_time":0.3785247523},
{"learn":[0.3086242844],"iteration":55,"passed_time":0.4708062433,"remaining_time":0.3699191912},
{"learn":[0.3085739808],"iteration":56,"passed_time":0.4784593991,"remaining_time":0.3609430555},
{"learn":[0.3085362197],"iteration":57,"passed_time":0.4867871893,"remaining_time":0.3525010681},
{"learn":[0.3084985251],"iteration":58,"passed_time":0.4935030662,"remaining_time":0.3429428087},
{"learn":[0.3084665796],"iteration":59,"passed_time":0.5013063238,"remaining_time":0.3342042159},
{"learn":[0.3084414859],"iteration":60,"passed_time":0.5090891726,"remaining_time":0.3254832415},
{"learn":[0.3084208472],"iteration":61,"passed_time":0.5176549323,"remaining_time":0.3172723779},
{"learn":[0.3083895614],"iteration":62,"passed_time":0.5261203062,"remaining_time":0.3089912909},
{"learn":[0.3083714774],"iteration":63,"passed_time":0.5347114176,"remaining_time":0.3007751724},
{"learn":[0.3083563016],"iteration":64,"passed_time":0.5421899667,"remaining_time":0.2919484436},
{"learn":[0.3083431053],"iteration":65,"passed_time":0.5503965921,"remaining_time":0.2835376384},
{"learn":[0.3083377974],"iteration":66,"passed_time":0.5578064912,"remaining_time":0.2747405106},
{"learn":[0.3083267736],"iteration":67,"passed_time":0.5658731138,"remaining_time":0.26629323},
{"learn":[0.3083249267],"iteration":68,"passed_time":0.5733717259,"remaining_time":0.2576017899},
{"learn":[0.3083079171],"iteration":69,"passed_time":0.5814975124,"remaining_time":0.2492132196},
{"learn":[0.3083002137],"iteration":70,"passed_time":0.5889929226,"remaining_time":0.240574574},
{"learn":[0.3082893058],"iteration":71,"passed_time":0.5966887426,"remaining_time":0.2320456221},
{"learn":[0.3082866281],"iteration":72,"passed_time":0.6052630366,"remaining_time":0.2238644108},
{"learn":[0.3082840611],"iteration":73,"passed_time":0.6123525549,"remaining_time":0.2151508977},
{"learn":[0.3082810677],"iteration":74,"passed_time":0.6208448172,"remaining_time":0.2069482724},
{"learn":[0.3082786328],"iteration":75,"passed_time":0.6284333687,"remaining_time":0.1984526428},
{"learn":[0.3082714374],"iteration":76,"passed_time":0.6381076852,"remaining_time":0.1906035943},
{"learn":[0.3082619247],"iteration":77,"passed_time":0.6471685323,"remaining_time":0.1825347142},
{"learn":[0.3082606269],"iteration":78,"passed_time":0.6553918713,"remaining_time":0.1742180924},
{"learn":[0.3082443964],"iteration":79,"passed_time":0.662743489,"remaining_time":0.1656858723},
{"learn":[0.3082409299],"iteration":80,"passed_time":0.6728467921,"remaining_time":0.1578282599},
{"learn":[0.3082354642],"iteration":81,"passed_time":0.6804471801,"remaining_time":0.1493664542},
{"learn":[0.3082262923],"iteration":82,"passed_time":0.6881056136,"remaining_time":0.1409372944},
{"learn":[0.308223415],"iteration":83,"passed_time":0.6966173204,"remaining_time":0.1326890134},
{"learn":[0.3082182793],"iteration":84,"passed_time":0.7040058316,"remaining_time":0.1242363232},
{"learn":[0.3082049649],"iteration":85,"passed_time":0.711525709,"remaining_time":0.1158297666},
{"learn":[0.3082026264],"iteration":86,"passed_time":0.719250043,"remaining_time":0.1074741444},
{"learn":[0.3081922674],"iteration":87,"passed_time":0.7268714353,"remaining_time":0.09911883209},
{"learn":[0.3081806359],"iteration":88,"passed_time":0.7363648885,"remaining_time":0.09101139071},
{"learn":[0.3081779116],"iteration":89,"passed_time":0.7445351661,"remaining_time":0.08272612956},
{"learn":[0.3081755133],"iteration":90,"passed_time":0.7528657354,"remaining_time":0.07445924856},
{"learn":[0.3081744608],"iteration":91,"passed_time":0.7609579482,"remaining_time":0.06617025637},
{"learn":[0.3081657035],"iteration":92,"passed_time":0.7693967138,"remaining_time":0.05791158061},
{"learn":[0.3081643492],"iteration":93,"passed_time":0.7765516702,"remaining_time":0.04956712789},
{"learn":[0.3081618283],"iteration":94,"passed_time":0.7845056397,"remaining_time":0.04128977051},
{"learn":[0.3081615742],"iteration":95,"passed_time":0.7918163387,"remaining_time":0.03299234745},
{"learn":[0.3081599282],"iteration":96,"passed_time":0.8003260771,"remaining_time":0.0247523529},
{"learn":[0.3081575212],"iteration":97,"passed_time":0.8084868304,"remaining_time":0.01649973123},
{"learn":[0.3081519358],"iteration":98,"passed_time":0.8169988485,"remaining_time":0.008252513621},
{"learn":[0.3081429789],"iteration":99,"passed_time":0.8247092756,"remaining_time":0}
]}